{
  "company": [
    {
      "name": "TESLA",
      "profit": "666 088 000",
      "id": 1
    },
    {
      "name": "GOOGLE",
      "profit": "16 155 000 000",
      "id": 2
    },
    {
      "name": "AMAZON",
      "profit": "2 208 000 000",
      "id": 3
    },
    {
      "name": "MICROSOFT",
      "profit": "24 800 000 000",
      "id": 4
    },
    {
      "name": "PAYPAL",
      "profit": "14 214 000 000",
      "id": 5
    },
    {
      "name": "EBAY",
      "profit": "3 310 000 000",
      "id": 6
    }
  ]
}